{
  "buildCommand" : {
    "command" : "build",
    "skipDependencies" : false,
    "style" : "buildAndRun"
  },
  "configuredTargets" : [
    {
      "guid" : "083b243bd47837829dcb7fb7b593b8edc7532994f9281f2188368a7b0d0876a9"
    }
  ],
  "containerPath" : "/Users/menyawino/Playground/Aamal/Aamal/Aamal.xcodeproj",
  "continueBuildingAfterErrors" : false,
  "dependencyScope" : "workspace",
  "enableIndexBuildArena" : false,
  "hideShellScriptEnvironment" : false,
  "parameters" : {
    "action" : "build",
    "overrides" : {
      "commandLine" : {
        "table" : {

        }
      },
      "synthesized" : {
        "table" : {
          "ACTION" : "build",
          "COLOR_DIAGNOSTICS" : "YES",
          "diagnostic_message_length" : "72",
          "ENABLE_PREVIEWS" : "NO",
          "ENABLE_XOJIT_PREVIEWS" : "NO"
        }
      }
    }
  },
  "showNonLoggedProgress" : true,
  "useDryRun" : false,
  "useImplicitDependencies" : false,
  "useLegacyBuildLocations" : false,
  "useParallelTargets" : true
}